README.rst
setup.py
bula/__init__.py
bula/image_extractor.py
bula/license_generator.py
bula/schema_generator.py
bula.egg-info/PKG-INFO
bula.egg-info/SOURCES.txt
bula.egg-info/dependency_links.txt
bula.egg-info/requires.txt
bula.egg-info/top_level.txt
bula/static/css/highlight.less
bula/static/css/main.less
bula/templates/adsense.html
bula/templates/analytics.html
bula/templates/archives.html
bula/templates/article.html
bula/templates/article_infos.html
bula/templates/article_list.html
bula/templates/base.html
bula/templates/category.html
bula/templates/comments.html
bula/templates/disqus_script.html
bula/templates/github.html
bula/templates/index.html
bula/templates/mailchimp.html
bula/templates/meta_tags.html
bula/templates/page.html
bula/templates/pagination.html
bula/templates/period_archives.html
bula/templates/related_posts.html
bula/templates/social.html
bula/templates/tag.html
bula/templates/taglist.html
bula/templates/tags.html
bula/templates/translations.html