Metadata-Version: 1.2
Name: bula
Version: 0.2.55
Summary: Bula theme for Pelican
Home-page: https://github.com/yostos/bula
Author: Toshiyuki Yoshida
Author-email: yostos@yostos.org
Maintainer: Toshiyuki Yoshida
Maintainer-email: yostos@yostos.org
License: ISC
Platform: UNKNOWN
Classifier: Development Status :: 4 - Beta
Classifier: Framework :: Pelican :: Themes
Classifier: License :: OSI Approved :: ISC License (ISCL)
Classifier: Programming Language :: Python :: 3 :: Only
